{
  "meta": {
    "collectedAt": "2025-12-30T06:38:47.809Z",
    "repository": "holiber/barducks",
    "eventName": "push",
    "sha": "d176326ec21269ec864621e3e37539f8f27478ee",
    "ref": "refs/heads/main",
    "runId": "20590606807",
    "runAttempt": "1",
    "prNumber": 106,
    "prUrl": "https://github.com/holiber/barducks/pull/106",
    "node": "v24.12.0"
  },
  "pr": 106,
  "commands": {
    "npm_test": {
      "name": "npm_test",
      "command": "bash -lc 'npx c8 --reporter=json-summary --report-dir .cache/coverage npm run test:unit || (echo \"⚠️ Unit tests failed, retrying after 60 seconds...\"; sleep 60; npx c8 --reporter=json-summary --report-dir .cache/coverage npm run test:unit)'",
      "exitCode": 0,
      "durationMs": 31013,
      "collectedAt": "2025-12-30T06:37:59.805Z"
    },
    "pw_installer": {
      "name": "pw_installer",
      "command": "bash -lc 'npx playwright test -c tests/installer/playwright.config.ts || (echo \"⚠️ Playwright installer suite failed, retrying after 60 seconds...\"; sleep 60; npx playwright test -c tests/installer/playwright.config.ts)'",
      "exitCode": 0,
      "durationMs": 28365,
      "collectedAt": "2025-12-30T06:38:47.243Z"
    },
    "npm_pack": {
      "name": "npm-pack",
      "command": "npm pack --silent",
      "exitCode": 0,
      "durationMs": 844
    }
  },
  "sizes": {
    "npm_pack": {
      "bytes": 3624169
    }
  },
  "tests": {
    "unit": {
      "total": 83,
      "suites": 16,
      "passed": 74,
      "failed": 0,
      "skipped": 9,
      "reportedDurationMs": 28143.85932,
      "durationMs": 31013,
      "exitCode": 0
    },
    "e2e_installer": {
      "total": 34,
      "passed": 34,
      "reportedDurationMs": 27100,
      "durationMs": 28365,
      "exitCode": 0
    },
    "flaky": {
      "count": 0
    }
  },
  "code": {
    "scriptCodeLines": 35848,
    "totalTextLines": 46931,
    "hugeScripts": 3
  },
  "quality": {
    "coverage": {
      "linesPct": 63.28,
      "statementsPct": 63.28,
      "branchesPct": 60.86,
      "functionsPct": 64.82
    },
    "slowTests": {
      "thresholdMs": 20000,
      "count": 0,
      "bySuite": {
        "unit": {
          "count": 0,
          "top": []
        }
      }
    },
    "duplication": {
      "duplicatedPct": 8.76,
      "duplicatedLines": 2764,
      "totalLines": 31552
    }
  },
  "notes": [
    "BUILD_COMMAND not set; build metric skipped.",
    "DEV_COMMAND not set; dev startup metric skipped."
  ],
  "commit": "d176326ec21269ec864621e3e37539f8f27478ee",
  "timestamp": "2025-12-30T06:38:52.835Z",
  "baseline": {
    "commit": "d176326ec21269ec864621e3e37539f8f27478ee",
    "pr": 106,
    "timestamp": "2025-12-30T06:38:52.835Z"
  }
}
