{
  "meta": {
    "collectedAt": "2025-12-30T04:10:53.526Z",
    "repository": "holiber/barducks",
    "eventName": "push",
    "sha": "150cb5fd6152076059848c22e0271d2e5999ef04",
    "ref": "refs/heads/main",
    "runId": "20588626675",
    "runAttempt": "1",
    "prNumber": 102,
    "prUrl": "https://github.com/holiber/barducks/pull/102",
    "node": "v24.12.0"
  },
  "pr": {
    "number": 102,
    "url": "https://github.com/holiber/barducks/pull/102"
  },
  "commands": {
    "npm_test": {
      "name": "npm_test",
      "command": "bash -lc 'npx c8 --reporter=json-summary --report-dir .cache/coverage npm run test:unit || (echo \"⚠️ Unit tests failed, retrying after 60 seconds...\"; sleep 60; npx c8 --reporter=json-summary --report-dir .cache/coverage npm run test:unit)'",
      "exitCode": 0,
      "durationMs": 32198,
      "collectedAt": "2025-12-30T04:10:06.462Z"
    },
    "pw_installer": {
      "name": "pw_installer",
      "command": "bash -lc 'npx playwright test -c tests/installer/playwright.config.ts || (echo \"⚠️ Playwright installer suite failed, retrying after 60 seconds...\"; sleep 60; npx playwright test -c tests/installer/playwright.config.ts)'",
      "exitCode": 0,
      "durationMs": 29482,
      "collectedAt": "2025-12-30T04:10:52.956Z"
    },
    "npm_pack": {
      "name": "npm-pack",
      "command": "npm pack --silent",
      "exitCode": 0,
      "durationMs": 835
    }
  },
  "sizes": {
    "npm_pack": {
      "bytes": 3624285
    }
  },
  "tests": {
    "unit": {
      "total": 83,
      "suites": 16,
      "passed": 74,
      "failed": 0,
      "skipped": 9,
      "reportedDurationMs": 29325.935118,
      "durationMs": 32198,
      "exitCode": 0
    },
    "e2e_installer": {
      "total": 34,
      "passed": 34,
      "reportedDurationMs": 28200,
      "durationMs": 29482,
      "exitCode": 0
    },
    "flaky": {
      "count": 0
    }
  },
  "code": {
    "scriptCodeLines": 35750,
    "totalTextLines": 47073,
    "hugeScripts": 3
  },
  "quality": {
    "coverage": {
      "linesPct": 63.28,
      "statementsPct": 63.28,
      "branchesPct": 60.86,
      "functionsPct": 64.82
    },
    "slowTests": {
      "thresholdMs": 20000,
      "count": 0,
      "bySuite": {
        "unit": {
          "count": 0,
          "top": []
        }
      }
    },
    "duplication": {
      "duplicatedPct": 8.79,
      "duplicatedLines": 2764,
      "totalLines": 31454
    }
  },
  "notes": [
    "BUILD_COMMAND not set; build metric skipped.",
    "DEV_COMMAND not set; dev startup metric skipped."
  ]
}
